LICENSE
sdevtools/__init__.py
sdevtools/__main__.py
sdevtools/debug.py
sdevtools/prettier.py
sdevtools/style.py
sdevtools/timer.py
sdevtools/utils.py
sdevtools/version.py
sha_python_devtools-0.1.6.dist-info/LICENSE
sha_python_devtools-0.1.6.dist-info/WHEEL
sha_python_devtools-0.1.6.dist-info/METADATA
sha_python_devtools-0.1.6.dist-info/RECORD
